{
	"configurations" : 
	[
		{
			"directories" : 
			[
				{
					"build" : ".",
					"jsonFile" : "directory-.-Debug-f5ebdc15457944623624.json",
					"minimumCMakeVersion" : 
					{
						"string" : "3.29"
					},
					"projectIndex" : 0,
					"source" : ".",
					"targetIndexes" : 
					[
						0
					]
				}
			],
			"name" : "Debug",
			"projects" : 
			[
				{
					"directoryIndexes" : 
					[
						0
					],
					"name" : "To_Do_List",
					"targetIndexes" : 
					[
						0
					]
				}
			],
			"targets" : 
			[
				{
					"directoryIndex" : 0,
					"id" : "To_Do_List::@6890427a1f51a3e7e1df",
					"jsonFile" : "target-To_Do_List-Debug-3a439f8543109ccd4b63.json",
					"name" : "To_Do_List",
					"projectIndex" : 0
				}
			]
		}
	],
	"kind" : "codemodel",
	"paths" : 
	{
		"build" : "/Users/samisubei/Documents/GitHub/To-Do-List/cmake-build-debug",
		"source" : "/Users/samisubei/Documents/GitHub/To-Do-List"
	},
	"version" : 
	{
		"major" : 2,
		"minor" : 7
	}
}
